lyraml/__init__.py
lyraml/dataset.py
lyraml/judge.py
lyraml/utils/__init__.py
lyraml/utils/constants.py
lyraml/utils/display_util.py
lyraml/utils/entity.py
lyraml/utils/error_handling.py
lyraml/utils/file.py
lyraml/utils/firebase.py
lyraml/utils/source_code.py
lyraml-0.0.2024062701.dist-info/METADATA
lyraml-0.0.2024062701.dist-info/WHEEL
lyraml-0.0.2024062701.dist-info/top_level.txt
lyraml-0.0.2024062701.dist-info/RECORD
