Metadata-Version: 2.1
Name: lyraml
Version: 0.0.2024062701
Summary: lyraml
Keywords: python,first package
Classifier: Development Status :: 3 - Alpha
Classifier: Intended Audience :: Education
Classifier: Programming Language :: Python :: 2
Classifier: Programming Language :: Python :: 3
Classifier: Operating System :: MacOS :: MacOS X
Classifier: Operating System :: Microsoft :: Windows
Requires-Dist: certifi ==2024.6.2
Requires-Dist: charset-normalizer ==3.3.2
Requires-Dist: idna ==3.7
Requires-Dist: python-dotenv ==1.0.1
Requires-Dist: requests ==2.32.3
Requires-Dist: urllib3 ==2.2.2
